lsyiot_livegbs_sdk/__init__.py
lsyiot_livegbs_sdk/api.py
lsyiot_livegbs_sdk/exceptions.py
lsyiot_livegbs_sdk/responses.py
lsyiot_livegbs_sdk-1.0.1.dist-info/licenses/LICENSE
lsyiot_livegbs_sdk-1.0.1.dist-info/METADATA
lsyiot_livegbs_sdk-1.0.1.dist-info/WHEEL
lsyiot_livegbs_sdk-1.0.1.dist-info/top_level.txt
lsyiot_livegbs_sdk-1.0.1.dist-info/RECORD
