Metadata-Version: 2.4
Name: lsyiot-livegbs-sdk
Version: 1.0.1
Summary: LiveGBS GB28181国标流媒体服务Python接口
Home-page: https://github.com/9kl/lsyiot_livegbs_sdk
Author: fhp
Author-email: fhp <chinafengheping@outlook.com>
License: Apache-2.0
Project-URL: Homepage, https://github.com/9kl/lsyiot_livegbs_sdk
Project-URL: Documentation, https://github.com/9kl/lsyiot_livegbs_sdk#readme
Project-URL: Repository, https://github.com/9kl/lsyiot_livegbs_sdk.git
Project-URL: Bug Tracker, https://github.com/9kl/lsyiot_livegbs_sdk/issues
Keywords: livegbs,gb28181,streaming,video,surveillance,sdk
Classifier: Development Status :: 5 - Production/Stable
Classifier: Intended Audience :: Developers
Classifier: License :: OSI Approved :: Apache Software License
Classifier: Operating System :: OS Independent
Classifier: Programming Language :: Python :: 3
Classifier: Programming Language :: Python :: 3.8
Classifier: Programming Language :: Python :: 3.9
Classifier: Programming Language :: Python :: 3.10
Classifier: Programming Language :: Python :: 3.11
Classifier: Programming Language :: Python :: 3.12
Classifier: Topic :: Software Development :: Libraries :: Python Modules
Classifier: Topic :: Multimedia :: Video
Classifier: Topic :: System :: Networking
Requires-Python: >=3.8
License-File: LICENSE
Requires-Dist: requests>=2.25.0
Dynamic: author
Dynamic: home-page
Dynamic: license-file
Dynamic: requires-python
